langswarm/__init__.py
langswarm/cli/deps.py
langswarm/cli/init.py
langswarm/config/token_tracking_config.yaml
langswarm/core/__init__.py
langswarm/core/agents/__init__.py
langswarm/core/agents/base.py
langswarm/core/agents/base_create.py
langswarm/core/agents/builder.py
langswarm/core/agents/cost/__init__.py
langswarm/core/agents/cost/billing.py
langswarm/core/agents/cost/budget.py
langswarm/core/agents/cost/interfaces.py
langswarm/core/agents/cost/manager.py
langswarm/core/agents/cost/optimizer.py
langswarm/core/agents/cost/predictor.py
langswarm/core/agents/cost/recommendations.py
langswarm/core/agents/cost/tracker.py
langswarm/core/agents/interfaces.py
langswarm/core/agents/memory/README.md
langswarm/core/agents/memory/__init__.py
langswarm/core/agents/memory/implementations.py
langswarm/core/agents/memory/interfaces.py
langswarm/core/agents/multimodal.py
langswarm/core/agents/multimodal_agent.py
langswarm/core/agents/multimodal_processor.py
langswarm/core/agents/pools/__init__.py
langswarm/core/agents/pools/base.py
langswarm/core/agents/pools/interfaces.py
langswarm/core/agents/pools/load_balancer.py
langswarm/core/agents/pools/manager.py
langswarm/core/agents/pools/monitoring.py
langswarm/core/agents/pools/providers.py
langswarm/core/agents/provider_registry.py
langswarm/core/agents/providers/__init__.py
langswarm/core/agents/providers/anthropic.py
langswarm/core/agents/providers/anthropic_multimodal.py
langswarm/core/agents/providers/cohere.py
langswarm/core/agents/providers/config.py
langswarm/core/agents/providers/custom_template.py
langswarm/core/agents/providers/gemini.py
langswarm/core/agents/providers/gemini_multimodal.py
langswarm/core/agents/providers/huggingface.py
langswarm/core/agents/providers/litellm.py
langswarm/core/agents/providers/local.py
langswarm/core/agents/providers/mistral.py
langswarm/core/agents/providers/openai.py
langswarm/core/agents/providers/openai_multimodal.py
langswarm/core/agents/realtime/__init__.py
langswarm-0.1.0.dist-info/METADATA
langswarm-0.1.0.dist-info/WHEEL
langswarm-0.1.0.dist-info/licenses/LICENSE
langswarm-0.1.0.dist-info/RECORD
