Metadata-Version: 2.4
Name: langswarm
Version: 0.1.0
Summary: A multi-agent ecosystem for large language models (LLMs) and autonomous systems.
License: MIT
License-File: LICENSE
Keywords: LLM,multi-agent,agentic,openai,MCP,agent,orchestration,langswarm,autonomous
Author: Alexander Ekdahl
Author-email: alexander.ekdahl@gmail.com
Requires-Python: >=3.8,<4.0
Classifier: License :: OSI Approved :: MIT License
Classifier: Programming Language :: Python :: 3
Classifier: Programming Language :: Python :: 3.8
Classifier: Programming Language :: Python :: 3.9
Classifier: Programming Language :: Python :: 3.10
Classifier: Programming Language :: Python :: 3.11
Classifier: Programming Language :: Python :: 3.12
Classifier: Programming Language :: Python :: 3.13
Classifier: Programming Language :: Python :: 3.14
Provides-Extra: all
Provides-Extra: bigquery
Provides-Extra: daytona
Provides-Extra: dev
Provides-Extra: google-workspace
Provides-Extra: observability
Provides-Extra: opentelemetry
Requires-Dist: aiohttp (>=3.11.18,<4.0.0)
Requires-Dist: aioredis (>=2.0.1,<3.0.0)
Requires-Dist: botbuilder (>=0.0.1,<0.0.2)
Requires-Dist: boto3 (>=1.38.18,<2.0.0)
Requires-Dist: cerberus (>=1.3.7,<2.0.0)
Requires-Dist: daytona (>=0.10.5,<0.11.0) ; extra == "daytona" or extra == "all"
Requires-Dist: discord-py (>=2.5.2,<3.0.0)
Requires-Dist: docker-py (>=1.10.6,<2.0.0)
Requires-Dist: fastapi (>=0.115.12,<0.116.0)
Requires-Dist: flask (>=3.1.1,<4.0.0)
Requires-Dist: functions-framework (>=3.8.3,<4.0.0)
Requires-Dist: google-api-python-client (>=2.118.0,<3.0.0) ; extra == "google-workspace" or extra == "all"
Requires-Dist: google-auth-oauthlib (>=1.2.0,<2.0.0) ; extra == "google-workspace" or extra == "all"
Requires-Dist: google-cloud-bigquery (>=3.0.0,<4.0.0) ; extra == "bigquery" or extra == "all"
Requires-Dist: google-cloud-bigquery-storage (>=2.0.0,<3.0.0) ; extra == "bigquery" or extra == "all"
Requires-Dist: google-cloud-pubsub
Requires-Dist: ipython (>=8.12.3,<9.0.0)
Requires-Dist: ipywidgets (>=8.1.7,<9.0.0)
Requires-Dist: jinja2 (>=3.1.6,<4.0.0)
Requires-Dist: langchain-community (>=0.3.24,<0.4.0)
Requires-Dist: langchain-openai (>=0.3.17,<0.4.0)
Requires-Dist: langfuse (>=2.53.0,<3.0.0) ; extra == "observability"
Requires-Dist: langsmith (>=0.3.42,<0.4.0)
Requires-Dist: langswarm-memory (>=0.2.0,<0.3.0)
Requires-Dist: litellm (>=1.74.0,<2.0.0)
Requires-Dist: llama-index (>=0.12.36,<0.13.0)
Requires-Dist: nest-asyncio (>=1.6.0,<2.0.0)
Requires-Dist: openai (>=1.79.0,<2.0.0)
Requires-Dist: opentelemetry-api (>=1.21.0,<2.0.0) ; extra == "opentelemetry" or extra == "all"
Requires-Dist: opentelemetry-exporter-jaeger (>=1.21.0,<2.0.0) ; extra == "opentelemetry" or extra == "all"
Requires-Dist: opentelemetry-exporter-otlp (>=1.21.0,<2.0.0) ; extra == "opentelemetry" or extra == "all"
Requires-Dist: opentelemetry-exporter-prometheus (>=1.12.0rc1,<2.0.0) ; extra == "opentelemetry" or extra == "all"
Requires-Dist: opentelemetry-instrumentation (>=0.42b0,<0.43) ; extra == "opentelemetry" or extra == "all"
Requires-Dist: opentelemetry-sdk (>=1.21.0,<2.0.0) ; extra == "opentelemetry" or extra == "all"
Requires-Dist: pinecone (>=6.0.2,<7.0.0)
Requires-Dist: pydantic (>=2.11.4,<3.0.0)
Requires-Dist: python-telegram-bot (>=22.1,<23.0)
Requires-Dist: pyyaml (>=6.0.2,<7.0.0)
Requires-Dist: qdrant-client (>=1.14.2,<2.0.0)
Requires-Dist: redis
Requires-Dist: requests (>=2.32.3,<3.0.0)
Requires-Dist: simpleeval (>=1.0.3,<2.0.0)
Requires-Dist: slack-bolt (>=1.23.0,<2.0.0)
Requires-Dist: tiktoken (>=0.9.0,<0.10.0)
Requires-Dist: transformers (>=4.51.3,<5.0.0)
Requires-Dist: twilio (>=9.6.1,<10.0.0)
Requires-Dist: uvicorn (>=0.34.2,<0.35.0)
Requires-Dist: websockets (>=13.1,<14.0)
Project-URL: Homepage, https://github.com/aekdahl/langswarm
Project-URL: Repository, https://github.com/aekdahl/langswarm
